base/memoria.py
gerador/palavras.py
gerador_de_palavras-0.0.2.dist-info/LICENSE
gerador_de_palavras-0.0.2.dist-info/METADATA
gerador_de_palavras-0.0.2.dist-info/WHEEL
gerador_de_palavras-0.0.2.dist-info/top_level.txt
gerador_de_palavras-0.0.2.dist-info/RECORD
