Metadata-Version: 2.1
Name: gerador-de-palavras
Version: 0.0.2
Summary: Pacote python para gerar palavras aleatórias
Home-page: UNKNOWN
Author: Let lima
Author-email: lwtferr@gmail.com
License: MIT License
Keywords: Pacote
Platform: UNKNOWN
License-File: LICENSE
Requires-Dist: numpy
